mewtools/__init__.py
mewtools/__version__.py
mewtools/mydatetime/__init__.py
mewtools/mydatetime/core.py
mewtools/mydatetime/extract_.py
mewtools/mydatetime/extract_prep.py
mewtools/mydatetime/month_pair.py
mewtools/mydatetime/timezone.py
mewtools/wordpress/__init__.py
mewtools/wordpress/category.py
mewtools/wordpress/core.py
mewtools/wordpress/custom.py
mewtools/wordpress/files.py
mewtools/wordpress/posts.py
mewtools-0.1.13.dist-info/LICENSE
mewtools-0.1.13.dist-info/METADATA
mewtools-0.1.13.dist-info/WHEEL
mewtools-0.1.13.dist-info/top_level.txt
mewtools-0.1.13.dist-info/RECORD
