Metadata-Version: 2.1
Name: mewtools
Version: 0.1.13
Summary: My python library package with some scraper tool and data tool
Home-page: https://github.com/sizzlingbun/mewtools
Author: Andrew
Author-email: me@example.com
License: MIT
Classifier: License :: OSI Approved :: MIT License
Classifier: Programming Language :: Python :: 3
Requires-Python: >=3.10.0
License-File: LICENSE
Requires-Dist: addict ==2.4.0
Requires-Dist: carehttp >=0.3.11
Requires-Dist: certifi ==2022.5.18.1
Requires-Dist: charset-normalizer ==2.0.12
Requires-Dist: colorama ==0.4.4
Requires-Dist: date-extractor ==5.1.5
Requires-Dist: dateparser ==1.1.1
Requires-Dist: filetype ==1.0.13
Requires-Dist: humanize ==4.1.0
Requires-Dist: idna >=2.8
Requires-Dist: loguru ==0.6.0
Requires-Dist: maya ==0.6.1
Requires-Dist: pendulum ==2.1.2
Requires-Dist: python-dateutil ==2.8.2
Requires-Dist: pytz ==2022.1
Requires-Dist: pytz-deprecation-shim ==0.1.0.post0
Requires-Dist: pytzdata ==2020.1
Requires-Dist: regex ==2022.3.2
Requires-Dist: requests >=2.22.0
Requires-Dist: requests-toolbelt ==0.9.1
Requires-Dist: retrying ==1.3.3
Requires-Dist: six ==1.16.0
Requires-Dist: snaptime ==0.2.4
Requires-Dist: tzdata
Requires-Dist: tzlocal ==4.2
Requires-Dist: urllib3 >=1.25.11
Requires-Dist: win32-setctime ==1.1.0
Requires-Dist: arrow ~=1.2.2
